snapstitch-0.1.2.dist-info/METADATA
snapstitch-0.1.2.dist-info/WHEEL
snapstitch-0.1.2.dist-info/entry_points.txt
snapstitch-0.1.2.dist-info/licenses/LICENSE
snapstitch/__init__.py
snapstitch/data.py
snapstitch/generator.py
snapstitch/stitch.py
snapstitch-0.1.2.dist-info/RECORD
