Metadata-Version: 2.1
Name: snapstitch
Version: 0.1.2
Summary: An open-source python library to generate synthetic datasets for computer vision tasks
Author-Email: ram <justforthegreatergood@gmail.com>
License: MIT
Requires-Python: >=3.8
Requires-Dist: numpy>=1.24.4
Requires-Dist: opencv-python>=4.8.1.78
Requires-Dist: tqdm>=4.66.5
Requires-Dist: pytest-mock>=3.14.0
Requires-Dist: setuptools>=75.1.0
